jjjxutils/__init__.py
jjjxutils/archive/__init__.py
jjjxutils/archive/zip.py
jjjxutils/decorators.py
jjjxutils/imports.py
jjjxutils/rendering/__init__.py
jjjxutils/rendering/html.py
jjjxutils/web/__init__.py
jjjxutils/web/browser_client.py
jjjxutils-0.1.0.dist-info/LICENSE
jjjxutils-0.1.0.dist-info/METADATA
jjjxutils-0.1.0.dist-info/WHEEL
jjjxutils-0.1.0.dist-info/RECORD
