Metadata-Version: 2.1
Name: jjjxutils
Version: 0.1.0
Summary: 
License: MIT
Author: JoJoJux
Author-email: johannes@jojojux.de
Requires-Python: >=3.10,<4.0
Classifier: License :: OSI Approved :: MIT License
Classifier: Programming Language :: Python :: 3
Classifier: Programming Language :: Python :: 3.10
Classifier: Programming Language :: Python :: 3.11
Classifier: Programming Language :: Python :: 3.12
